src/README.md
src/__init__.py
src/cursor_mcp_plugin/MIGRATION.md
src/cursor_mcp_plugin/README.md
src/cursor_mcp_plugin/REFACTORING_SUMMARY.md
src/cursor_mcp_plugin/manifest.json
src/cursor_mcp_plugin/package-lock.json
src/cursor_mcp_plugin/package.json
src/cursor_mcp_plugin/setcharacters.js
src/cursor_mcp_plugin/tsconfig.json
src/cursor_mcp_plugin/ui.html
src/cursor_mcp_plugin/webpack.config.js
src/cursor_mcp_plugin/src/main.ts
src/cursor_mcp_plugin/src/commands/create/createFrame.ts
src/cursor_mcp_plugin/src/commands/create/createRectangle.ts
src/cursor_mcp_plugin/src/commands/create/index.ts
src/cursor_mcp_plugin/src/commands/document/exportNodeAsImage.ts
src/cursor_mcp_plugin/src/commands/document/getDocumentInfo.ts
src/cursor_mcp_plugin/src/commands/document/getInstanceOverrides.ts
src/cursor_mcp_plugin/src/commands/document/getNodeChildren.ts
src/cursor_mcp_plugin/src/commands/document/getNodeInfo.ts
src/cursor_mcp_plugin/src/commands/document/getSelection.ts
src/cursor_mcp_plugin/src/commands/document/index.ts
src/cursor_mcp_plugin/src/commands/style/index.ts
src/cursor_mcp_plugin/src/commands/style/setFillColor.ts
src/cursor_mcp_plugin/src/constants/index.ts
src/cursor_mcp_plugin/src/handlers/commandHandler.ts
src/cursor_mcp_plugin/src/services/progress.service.ts
src/cursor_mcp_plugin/src/services/storage.service.ts
src/cursor_mcp_plugin/src/types/index.ts
src/cursor_mcp_plugin/src/utils/helpers.ts
src/cursor_mcp_plugin/src/utils/node-filters.ts
src/figma_mcp/__init__.py
src/figma_mcp/figma_types.py
src/figma_mcp/file_manager.py
src/figma_mcp/server.py
src/figma_mcp/utils.py
src/figma_mcp/websocket_client.py
iflow_mcp_kdoronin_figma_mcp-0.1.1.dist-info/METADATA
iflow_mcp_kdoronin_figma_mcp-0.1.1.dist-info/WHEEL
iflow_mcp_kdoronin_figma_mcp-0.1.1.dist-info/entry_points.txt
iflow_mcp_kdoronin_figma_mcp-0.1.1.dist-info/RECORD
