Metadata-Version: 2.4
Name: iflow-mcp_kdoronin_figma_mcp
Version: 0.1.1
Summary: Figma Model Context Protocol (MCP) server using FastMCP framework
Requires-Python: >=3.8
Requires-Dist: fastmcp==2.4.0
Requires-Dist: pydantic==2.11.5
Requires-Dist: python-dotenv==1.1.0
Requires-Dist: typing-extensions==4.13.2
Requires-Dist: websocket-client==1.8.0
Requires-Dist: websockets==15.0.1
